pydicom_jpeg_decoder-0.2.0.dist-info/METADATA
pydicom_jpeg_decoder-0.2.0.dist-info/WHEEL
pydicom_jpeg_decoder-0.2.0.dist-info/licenses/LICENSE
pydicom_jpeg_decoder/__init__.py
pydicom_jpeg_decoder/pydicom_jpeg_decoder.cpython-313-darwin.so
pydicom_jpeg_decoder-0.2.0.dist-info/RECORD
