Metadata-Version: 2.4
Name: pydicom-jpeg-decoder
Version: 0.2.0
Classifier: Programming Language :: Rust
Classifier: Programming Language :: Python :: Implementation :: CPython
Classifier: Programming Language :: Python :: Implementation :: PyPy
Requires-Dist: pydicom>=2.4.4
License-File: LICENSE
Requires-Python: >=3.8
